calculator/__init__.py
abhishekcal-0.1.dist-info/LICENCE.txt
abhishekcal-0.1.dist-info/METADATA
abhishekcal-0.1.dist-info/WHEEL
abhishekcal-0.1.dist-info/top_level.txt
abhishekcal-0.1.dist-info/RECORD
