Metadata-Version: 2.1
Name: abhishekcal
Version: 0.1
Summary: This is a simple package
Home-page: UNKNOWN
Author: Abhishek Prashant Hatkar
Author-email: abhishek.hatkar@outlook.com
License: UNKNOWN
Platform: UNKNOWN
Classifier: Programming Language :: Python :: 3
Classifier: License :: OSI Approved :: MIT License
Classifier: Operating System :: OS Independent
License-File: LICENCE.txt
